breidablik/__init__.py
breidablik/grid_snapshot.py
breidablik/grid_snapshot.txt
breidablik/Balder/wavelengths.dat
breidablik/analysis/__init__.py
breidablik/analysis/format_read.py
breidablik/analysis/read.py
breidablik/analysis/test_read.py
breidablik/analysis/test_tools.py
breidablik/analysis/tools.py
breidablik/interpolate/__init__.py
breidablik/interpolate/grid_check.py
breidablik/interpolate/load.py
breidablik/interpolate/nlte.py
breidablik/interpolate/rew.py
breidablik/interpolate/scalar.py
breidablik/interpolate/spectra.py
breidablik/interpolate/test_grid_check.py
breidablik/interpolate/test_nlte.py
breidablik/interpolate/test_rew.py
breidablik/interpolate/test_scalar.py
breidablik/interpolate/test_spectra.py
breidablik/models/marcs/ffnn.json
breidablik/models/marcs/scalar.npy
breidablik/models/marcs/test.npy
breidablik/models/nlte/ffnn.json
breidablik/models/nlte/scalar.npy
breidablik/models/nlte/test.npy
breidablik/models/nlte_610/ffnn.json
breidablik/models/nlte_610/scalar.npy
breidablik/models/nlte_610/test.npy
breidablik/models/nlte_810/ffnn.json
breidablik/models/nlte_810/scalar.npy
breidablik/models/nlte_810/test.npy
breidablik/models/rbf/X.npy
breidablik/models/rbf/rbf.npy
breidablik/models/rbf/relative_err.npy
breidablik/models/rbf/scalar.npy
breidablik/models/rew/ffnn.json
breidablik/models/rew/scalar.npy
breidablik/models/rew/test.npy
breidablik/models/rew_610/ffnn.json
breidablik/models/rew_610/scalar.npy
breidablik/models/rew_610/test.npy
breidablik/models/rew_810/ffnn.json
breidablik/models/rew_810/scalar.npy
breidablik/models/rew_810/test.npy
breidablik-1.5.1.dist-info/LICENSE
breidablik-1.5.1.dist-info/METADATA
breidablik-1.5.1.dist-info/WHEEL
breidablik-1.5.1.dist-info/top_level.txt
breidablik-1.5.1.dist-info/RECORD
