Metadata-Version: 2.1
Name: breidablik
Version: 1.5.1
Summary: Interpolate lithium spectra and predict lithium abundance for most main sequence stars
Author-email: Ella Xi Wang <xi.wang3@anu.edu.au>
Project-URL: Homepage, https://github.com/ellawang44/Breidablik
Project-URL: Documentation, https://breidablik.readthedocs.io/en/latest/index.html
Project-URL: Repository, https://github.com/ellawang44/Breidablik.git
Project-URL: Issues, https://github.com/ellawang44/Breidablik/issues
Keywords: lithium,stellar,spectroscopy
Classifier: Development Status :: 3 - Alpha
Classifier: Intended Audience :: Science/Research
Classifier: Topic :: Scientific/Engineering :: Astronomy
Classifier: License :: OSI Approved :: MIT License
Classifier: Programming Language :: Python :: 3
Requires-Python: >=3.7
License-File: LICENSE
Requires-Dist: hypothesis >=4.17
Requires-Dist: numpy >=1.15
Requires-Dist: scipy >=1.3
Requires-Dist: pytest >=3.5
